{"wWRMQW8CezbELtBaSSGsJg==":"background13.jpeg","XSOx6KH/E8F0Za31r0JFrQ==":"background13-1.jpeg","XDRfeNguMh9Jzait1a1F3Q==":"background13-2.jpeg","65PjsXH+hhAv1iBRHS6O6g==":"background13-3.jpeg","PhiB2Ia35ualEjwSUO+5OA==":"renewdentalsupport-1280x853.jpeg","QZ8az5Jg4H/i9xYlgGAj5A==":"renewdentalicons%20(1)-1288x190.png","9NByw+iVU3UlZuaOq8l2pw==":"renewdentalicons%20(1)-1288x190.png","o9pTQ/QK4rprDSqp+D2ACQ==":"renewdentalicons%20(1)-506x75.png","vdj1vbHSBfOhjKeA2NlTrw==":"renewdentalicons%20(1)-506x75.png","l04fNcgO8GyZlUJzDuCEjA==":"renewdentalicons%20(1)-506x75.png","WpRQUTWasWS0gkvrEAg51w==":"renewdentalicons%20(1)-1450x1050.png","eznxU2bSSMA9pt8fZYjFxw==":"renewdentalicons%20(1)-1450x1050.png","hqzpdvpqH/duREoPRRDnuQ==":"renewdentalsupport-1280x853.jpg","faI7eifOhOrYtRlTYrHdXQ==":"image_2022_03_01t13_04_11_964z-1065x84.png","DT6N6cS/hwOivi8n6hZV1w==":"image_2022_03_01t13_04_11_964z-1-1065x84.png","LZcelk6H4QZKHOrLcJtaUQ==":"renewdentalicons%20(1)-1288x190.png","9EsSLDIgKOGRfu8kkvheCg==":"moneyback-150x132.png","A8Esdl+lCCYHSI/ERZuDow==":"moneyback-1-150x132.png","WxJnxyyyO8YwtVjmPSFSfw==":"moneyback-2-150x132.png","hI4GQhoV2zjKhbOla0rKYw==":"sans_titre__3_-removebg-preview-96x96.png","wy7PmSN+KZi4SFDqUBYk+g==":"sans_titre__3_-removebg-preview-1-96x96.png","Nx61tHuuWCGZCp1QAp2YoA==":"sans_titre__3_-removebg-preview-2-96x96.png","XbYvaeXS8Mu23w1i3UddyA==":"sans_titre__3_-removebg-preview-3-96x96.png","zJQo6tbXqMm1xuCQcCkGnA==":"sans_titre__3_-removebg-preview-4-96x96.png","FJWZbwpSFtDc81/SmuOnRw==":"sans_titre__3_-removebg-preview-5-96x96.png","J71U4eK6n7/Z8QFCX1VNdA==":"sans_titre__3_-removebg-preview-6-96x96.png","j8qacBtI6cWH7syAs04TPg==":"sans_titre__3_-removebg-preview-7-96x96.png","26DnbOWcN0MBKWby8zCfdw==":"sans_titre__3_-removebg-preview-8-96x96.png","GDGEicdNUzicW1i9qe/qqg==":"sans_titre__3_-removebg-preview-106x106.png","SbyEG7yWArTRyMWLR7MAfw==":"renewdentalsupport-removebg-preview-612x408.png","KpzCWtDnzEenF2Y/wn6oKw==":"mbr-1920x1920.png"}